pocket2linkwarden/__init__.py
pocket2linkwarden-0.1.1.dist-info/METADATA
pocket2linkwarden-0.1.1.dist-info/WHEEL
pocket2linkwarden-0.1.1.dist-info/entry_points.txt
pocket2linkwarden-0.1.1.dist-info/licenses/LICENSE
pocket2linkwarden-0.1.1.dist-info/RECORD
