Metadata-Version: 2.4
Name: pocket2linkwarden
Version: 0.1.1
Summary: Convert your Pocket bookmarks export to a Linkwarden-compatible HTML file.
Project-URL: Repository, https://github.com/fmhall/pocket2linkwarden
Author-email: Mason Hall <masonhall@gmail.com>
License-Expression: MIT
License-File: LICENSE
Keywords: bookmarks,export,linkwarden,pocket
Requires-Python: >=3.12
